helpmehelp-0.1.0.dist-info/METADATA
helpmehelp-0.1.0.dist-info/WHEEL
helpmehelp/__init__.py
helpmehelp/_core.abi3.so
helpmehelp/_core.pyi
helpmehelp/differential/__init__.py
helpmehelp/differential/discrete.py
helpmehelp/py.typed
helpmehelp-0.1.0.dist-info/RECORD
