Metadata-Version: 2.4
Name: helpmehelp
Version: 0.1.0
Requires-Dist: twine>=6.2.0
Summary: Add your description here
Author-email: helpmehelpgh <helpmehelp44@gmail.com>
Requires-Python: >=3.12
